toomanyports/__init__.py
toomanyports/core.py
toomanyports-0.1.11.dist-info/licenses/LICENSE
toomanyports-0.1.11.dist-info/METADATA
toomanyports-0.1.11.dist-info/WHEEL
toomanyports-0.1.11.dist-info/top_level.txt
toomanyports-0.1.11.dist-info/RECORD
