Metadata-Version: 2.4
Name: toomanyports
Version: 0.1.11
Summary: Port allocation cleanup usage reporting
Author: genderlesspit
License: MIT
Classifier: Programming Language :: Python :: 3
Classifier: License :: OSI Approved :: MIT License
Requires-Python: >=3.7
License-File: LICENSE
Requires-Dist: psutil
Requires-Dist: loguru
Dynamic: license-file
